COPYRIGHT
MANIFEST.in
Makefile
README
setup.py
test/__init__.py
test/__init__.pyc
test/test_compile.py
test/test_compile.pyc
test/test_simple.py
test/test_simple.pyc
tiddlywebplugins/__init__.py
tiddlywebplugins/relativetime.py
tiddlywebplugins.relativetime.egg-info/PKG-INFO
tiddlywebplugins.relativetime.egg-info/SOURCES.txt
tiddlywebplugins.relativetime.egg-info/dependency_links.txt
tiddlywebplugins.relativetime.egg-info/namespace_packages.txt
tiddlywebplugins.relativetime.egg-info/not-zip-safe
tiddlywebplugins.relativetime.egg-info/requires.txt
tiddlywebplugins.relativetime.egg-info/top_level.txt