Metadata-Version: 1.0
Name: tiddlywebplugins.relativetime
Version: 0.5
Summary: Use relative time expressions in select filters
Home-page: http://pypi.python.org/pypi/tiddlywebplugins.relativetime
Author: Chris Dent
Author-email: cdent@peermore.com
License: BSD
Platform: Posix; MacOS X; Windows
